ai_api_utils/__init__.py
ai_api_utils/main.py
ai_api_utils-1.0.2.dist-info/licenses/LICENSE
ai_api_utils-1.0.2.dist-info/METADATA
ai_api_utils-1.0.2.dist-info/WHEEL
ai_api_utils-1.0.2.dist-info/top_level.txt
ai_api_utils-1.0.2.dist-info/RECORD
